svconv/__init__.py
svconv-0.0.3.dist-info/METADATA
svconv-0.0.3.dist-info/WHEEL
svconv-0.0.3.dist-info/licenses/LICENSE
svconv-0.0.3.dist-info/RECORD
