Metadata-Version: 2.1
Name: svconv
Version: 0.0.3
Summary: A base spatially variant scalars implementation for pytorch convolutions
Project-URL: Homepage, https://github.com/jack-champagne/svconv
Project-URL: Bug Tracker, https://github.com/jack-champagne/svconv/issues
Author-email: Jack Champagne <jackchampagne.r@gmail.com>
License-File: LICENSE
Classifier: License :: OSI Approved :: GNU General Public License v3 (GPLv3)
Classifier: Programming Language :: Python :: 3
Requires-Python: >=3.7
